plato_helper_py/.scannerwork/.sonar_lock
plato_helper_py/.scannerwork/report-task.txt
plato_helper_py/.scannerwork/scanner-report/activerules.pb
plato_helper_py/.scannerwork/scanner-report/changesets-2.pb
plato_helper_py/.scannerwork/scanner-report/changesets-3.pb
plato_helper_py/.scannerwork/scanner-report/changesets-4.pb
plato_helper_py/.scannerwork/scanner-report/component-1.pb
plato_helper_py/.scannerwork/scanner-report/component-2.pb
plato_helper_py/.scannerwork/scanner-report/component-3.pb
plato_helper_py/.scannerwork/scanner-report/component-4.pb
plato_helper_py/.scannerwork/scanner-report/context-props.pb
plato_helper_py/.scannerwork/scanner-report/coverages-2.pb
plato_helper_py/.scannerwork/scanner-report/coverages-3.pb
plato_helper_py/.scannerwork/scanner-report/coverages-4.pb
plato_helper_py/.scannerwork/scanner-report/duplications-2.pb
plato_helper_py/.scannerwork/scanner-report/duplications-3.pb
plato_helper_py/.scannerwork/scanner-report/measures-2.pb
plato_helper_py/.scannerwork/scanner-report/measures-3.pb
plato_helper_py/.scannerwork/scanner-report/measures-4.pb
plato_helper_py/.scannerwork/scanner-report/metadata.pb
plato_helper_py/.scannerwork/scanner-report/source-2.txt
plato_helper_py/.scannerwork/scanner-report/source-3.txt
plato_helper_py/.scannerwork/scanner-report/source-4.txt
plato_helper_py/.scannerwork/scanner-report/symbols-2.pb
plato_helper_py/.scannerwork/scanner-report/symbols-3.pb
plato_helper_py/.scannerwork/scanner-report/symbols-4.pb
plato_helper_py/.scannerwork/scanner-report/syntax-highlightings-2.pb
plato_helper_py/.scannerwork/scanner-report/syntax-highlightings-3.pb
plato_helper_py/.scannerwork/scanner-report/syntax-highlightings-4.pb
plato_helper_py/__init__.py
plato_helper_py/api.py
plato_helper_py/py.typed
plato_helper_py/request_collections.py
plato_helper_py-2.1.1.dist-info/LICENSE
plato_helper_py-2.1.1.dist-info/WHEEL
plato_helper_py-2.1.1.dist-info/METADATA
plato_helper_py-2.1.1.dist-info/RECORD
