Metadata-Version: 2.1
Name: plato-helper-py
Version: 2.1.1
Summary: Helper for the Plato microservice
Author: Tiago Santos
Author-email: tiago.santos@vizidox.com
Requires-Python: >=3.7.2,<4.0.0
Classifier: Programming Language :: Python :: 3
Classifier: Programming Language :: Python :: 3.10
Classifier: Programming Language :: Python :: 3.8
Classifier: Programming Language :: Python :: 3.9
Requires-Dist: backoff (>=2.2,<3.0)
Requires-Dist: requests (>=2.27,<3.0)
Requires-Dist: types-requests (>=2.28.11,<3.0.0)
